kayvee/__init__.py
kayvee/kayvee.py
kayvee/logger.py
test/__init__.py
test/test_kayvee.py
test/test_logger.py
kayvee-3.0.0.dist-info/LICENSE
kayvee-3.0.0.dist-info/METADATA
kayvee-3.0.0.dist-info/WHEEL
kayvee-3.0.0.dist-info/top_level.txt
kayvee-3.0.0.dist-info/RECORD
