Metadata-Version: 2.1
Name: kayvee
Version: 3.0.0
Summary: Write data to key=val pairs, for human and machine readability
Home-page: https://github.com/Clever/kayvee-python/
Author: Clever
Author-email: tech-notify@getclever.com
License: UNKNOWN
Platform: UNKNOWN
Requires-Python: >=3.9.12
License-File: LICENSE
Requires-Dist: nose (>=1.0)
Requires-Dist: future (>=0.18.2)
